openbox/__init__.py
openbox/activities.py
openbox/activity_interceptor.py
openbox/config.py
openbox/otel_setup.py
openbox/py.typed
openbox/span_processor.py
openbox/tracing.py
openbox/types.py
openbox/worker.py
openbox/workflow_interceptor.py
openbox_temporal_sdk_python-1.0.0.dist-info/METADATA
openbox_temporal_sdk_python-1.0.0.dist-info/WHEEL
openbox_temporal_sdk_python-1.0.0.dist-info/licenses/LICENSE
openbox_temporal_sdk_python-1.0.0.dist-info/RECORD
