Metadata-Version: 2.4
Name: openbox-temporal-sdk-python
Version: 1.0.0
Summary: OpenBox SDK - Governance and observability for Temporal workflows
Project-URL: Homepage, https://github.com/OpenBox-AI/temporal-sdk-python
Project-URL: Documentation, https://github.com/OpenBox-AI/temporal-sdk-python#readme
Project-URL: Repository, https://github.com/OpenBox-AI/temporal-sdk-python.git
Project-URL: Issues, https://github.com/OpenBox-AI/temporal-sdk-python/issues
Project-URL: Changelog, https://github.com/OpenBox-AI/temporal-sdk-python/blob/main/CHANGELOG.md
Author-email: OpenBox Team <tino@openbox.ai>
License-Expression: MIT
License-File: LICENSE
Keywords: governance,hitl,human-in-the-loop,observability,opentelemetry,temporal,workflow
Classifier: Development Status :: 3 - Alpha
Classifier: Intended Audience :: Developers
Classifier: License :: OSI Approved :: MIT License
Classifier: Programming Language :: Python :: 3
Classifier: Programming Language :: Python :: 3.9
Classifier: Programming Language :: Python :: 3.10
Classifier: Programming Language :: Python :: 3.11
Classifier: Programming Language :: Python :: 3.12
Classifier: Topic :: Software Development :: Libraries :: Python Modules
Classifier: Topic :: System :: Monitoring
Classifier: Typing :: Typed
Requires-Python: >=3.9
Requires-Dist: asyncpg>=0.29.0
Requires-Dist: httpx<1,>=0.28.0
Requires-Dist: mysql-connector-python>=8.0.0
Requires-Dist: opentelemetry-api>=1.38.0
Requires-Dist: opentelemetry-instrumentation-asyncpg>=0.59b0
Requires-Dist: opentelemetry-instrumentation-httpx>=0.59b0
Requires-Dist: opentelemetry-instrumentation-mysql>=0.59b0
Requires-Dist: opentelemetry-instrumentation-psycopg2>=0.59b0
Requires-Dist: opentelemetry-instrumentation-pymongo>=0.59b0
Requires-Dist: opentelemetry-instrumentation-pymysql>=0.59b0
Requires-Dist: opentelemetry-instrumentation-redis>=0.59b0
Requires-Dist: opentelemetry-instrumentation-requests>=0.59b0
Requires-Dist: opentelemetry-instrumentation-sqlalchemy>=0.59b0
Requires-Dist: opentelemetry-instrumentation-urllib3>=0.59b0
Requires-Dist: opentelemetry-instrumentation-urllib>=0.59b0
Requires-Dist: opentelemetry-sdk>=1.38.0
Requires-Dist: psycopg2-binary>=2.9.10
Requires-Dist: pymongo>=4.0.0
Requires-Dist: pymysql>=1.0.0
Requires-Dist: redis>=5.0.0
Requires-Dist: sqlalchemy>=2.0.0
Requires-Dist: temporalio<2,>=1.8.0
